brianpackage/__init__.py
brianpackage/add.py
brianpackage/subtract.py
brianpackage/extras/__init__.py
brianpackage/extras/divide.py
brianpackage/extras/multiply.py
brianpackage-0.1.1.dist-info/METADATA
brianpackage-0.1.1.dist-info/WHEEL
brianpackage-0.1.1.dist-info/top_level.txt
brianpackage-0.1.1.dist-info/RECORD
